dokurestapi/__init__.py
dokurestapi/Login/__init__.py
dokurestapi/Users/__init__.py
dokurestapi-0.3.0.dist-info/LICENSE
dokurestapi-0.3.0.dist-info/METADATA
dokurestapi-0.3.0.dist-info/WHEEL
dokurestapi-0.3.0.dist-info/top_level.txt
dokurestapi-0.3.0.dist-info/RECORD
