Metadata-Version: 2.1
Name: dokurestapi
Version: 0.3.0
Summary: A Python package to interact with the DokuWiki REST API.
Home-page: https://github.com/krowvin/dokurestapi
Author: krowvin
Author-email: charlie@krowvin.com
License: MIT
Platform: UNKNOWN
Classifier: Programming Language :: Python :: 3
Classifier: License :: OSI Approved :: MIT License
Classifier: Operating System :: OS Independent
Requires-Python: >=3.6
Requires-Dist: requests
Requires-Dist: python-dotenv
